{"city": "San Francisco", "accidents": {"2012": [{"severity": "u'INJURY", "street1": "11THST", "street2": "'KISSLINGST", "date": "u'20120409", "year": "2012", "lat": 37.7726483, "lng": -122.4150145}, {"severity": "u'INJURY", "street1": "11THST", "street2": "u'MARKET", "date": "u'20120419", "year": "2012", "lat": 37.7724134, "lng": -122.4147158}, {"severity": "u'INJURY", "street1": "12THAV", "street2": "'FULTONST", "date": "u'20120313", "year": "2012", "lat": 37.7732078, "lng": -122.4701694}, {"severity": "u'INJURY", "street1": "12THST", "street2": "'FOLSOMST", "date": "u'20120306", "year": "2012", "lat": 37.7709294, "lng": -122.4150466}, {"severity": "u'INJURY", "street1": "13THST", "street2": "'HARRISONST", "date": "u'20120118", "year": "2012", "lat": 37.7696315, "lng": -122.413332}, {"severity": "u'INJURY", "street1": "13THST", "street2": "'HARRISONST", "date": "u'20120130", "year": "2012", "lat": 37.7696315, "lng": -122.413332}, {"severity": "u'INJURY", "street1": "13THST", "street2": "VANNESS", "date": "u'20120509", "year": "2012", "lat": 37.7697121, "lng": -122.4178256}, {"severity": "u'INJURY", "street1": "14THST", "street2": "'CHURCHST", "date": "u'20120206", "year": "2012", "lat": 37.7677354, "lng": -122.4289483}, {"severity": "u'INJURY", "street1": "14THST", "street2": "'GUERREROST", "date": "u'20120316", "year": "2012", "lat": 37.7680039, "lng": -122.4244975}, {"severity": "u'INJURY", "street1": "14THST", "street2": "'RAMONAAV", "date": "u'20120218", "year": "2012", "lat": 37.7679538, "lng": -122.4253988}, {"severity": "u'INJURY", "street1": "14THST", "street2": "'SHOTWELLST", "date": "u'20120202", "year": "2012", "lat": 37.7684817, "lng": -122.416711}, {"severity": "u'INJURY", "street1": "14THST", "street2": "VANNESS", "date": "u'20120104", "year": "2012", "lat": 37.7684217, "lng": -122.4178218}, {"severity": "u'INJURY", "street1": "14THST", "street2": "'VALENCIAST", "date": "u'20120829", "year": "2012", "lat": 37.7681528, "lng": -122.4222248}, {"severity": "u'INJURY", "street1": "16THST", "street2": "'ALABAMAST", "date": "u'20120815", "year": "2012", "lat": 37.7655043, "lng": -122.4124415}, {"severity": "u'INJURY", "street1": "16THST", "street2": "'ALBIONST", "date": "u'20120220", "year": "2012", "lat": 37.7648602, "lng": -122.422883}, {"severity": "u'INJURY", "street1": "16THST", "street2": "'BRYANTST", "date": "u'20120208", "year": "2012", "lat": 37.765618, "lng": -122.4105284}, {"severity": "u'INJURY", "street1": "16THST", "street2": "'CAPPST", "date": "u'20120729", "year": "2012", "lat": 37.7651267, "lng": -122.4186097}, {"severity": "u'INJURY", "street1": "16THST", "street2": "'FOLSOMST", "date": "u'20120526", "year": "2012", "lat": 37.7653296, "lng": -122.4153468}, {"severity": "u'INJURY", "street1": "16THST", "street2": "'MISSISSIPPIST", "date": "u'20120131", "year": "2012", "lat": 37.7666137, "lng": -122.3952032}, {"severity": "u'INJURY", "street1": "16THST", "street2": "'RONDELPL", "date": "u'20120809", "year": "2012", "lat": 37.7649612, "lng": -122.4212475}, {"severity": "u'INJURY", "street1": "17THST", "street2": "'CHURCHST", "date": "u'20120311", "year": "2012", "lat": 37.7628926, "lng": -122.428515}, {"severity": "u'PDO", "street1": "17THST", "street2": "'KANSASST", "date": "u'20120413", "year": "2012", "lat": 37.7647373, "lng": -122.4035493}, {"severity": "u'INJURY", "street1": "17THST", "street2": "'MISSIONST", "date": "u'20120515", "year": "2012", "lat": 37.7634242, "lng": -122.4195575}, {"severity": "u'INJURY", "street1": "17THST", "street2": "'MISSIONST", "date": "u'20120825", "year": "2012", "lat": 37.7634242, "lng": -122.4195575}, {"severity": "u'INJURY", "street1": "18THAV", "street2": "'ORTEGAST", "date": "u'20120725", "year": "2012", "lat": 37.7524181, "lng": -122.4752821}, {"severity": "u'INJURY", "street1": "18THST", "street2": "'GUERREROST", "date": "u'20120606", "year": "2012", "lat": 37.7615686, "lng": -122.4238021}, {"severity": "u'INJURY", "street1": "18THST", "street2": "'HATTIEST", "date": "u'20120607", "year": "2012", "lat": 37.7605308, "lng": -122.440918}, {"severity": "u'INJURY", "street1": "19THAV", "street2": "'BALBOAST", "date": "u'20120407", "year": "2012", "lat": 37.7765743, "lng": -122.4780402}, {"severity": "u'INJURY", "street1": "1STST", "street2": "'MARKETST", "date": "u'20120809", "year": "2012", "lat": 37.7910528, "lng": -122.3991866}, {"severity": "u'INJURY", "street1": "20THAV", "street2": "'KIRKHAMST", "date": "u'20120208", "year": "2012", "lat": 37.7597955, "lng": -122.4779532}, {"severity": "u'INJURY", "street1": "21STST", "street2": "'BARTLETTST", "date": "u'20120419", "year": "2012", "lat": 37.756969, "lng": -122.420011}, {"severity": "u'INJURY", "street1": "21STST", "street2": "'MISSIONST", "date": "u'20120417", "year": "2012", "lat": 37.7570308, "lng": -122.4189302}, {"severity": "u'INJURY", "street1": "22NDST", "street2": "'SANJOSEAV", "date": "u'20120227", "year": "2012", "lat": 37.7552793, "lng": -122.4214569}, {"severity": "u'INJURY", "street1": "24THST", "street2": "'HARRISONST", "date": "u'20120711", "year": "2012", "lat": 37.7526368, "lng": -122.4118888}, {"severity": "u'INJURY", "street1": "24THST", "street2": "'SVANNESSAV", "date": "u'20120110", "year": "2012", "lat": 37.7523682, "lng": -122.4162688}, {"severity": "u'INJURY", "street1": "24THST", "street2": "'VICKSBURGST", "date": "u'20120831", "year": "2012", "lat": 37.7516319, "lng": -122.4285462}, {"severity": "u'INJURY", "street1": "25THAV", "street2": "'ANZAST", "date": "u'20120827", "year": "2012", "lat": 37.7781536, "lng": -122.4845547}, {"severity": "u'INJURY", "street1": "25THAV", "street2": "'LAKEST", "date": "u'20120401", "year": "2012", "lat": 37.7857403, "lng": -122.4851044}, {"severity": "u'PDO", "street1": "2NDST", "street2": "'FOLSOMST", "date": "u'20120309", "year": "2012", "lat": 37.7855505, "lng": -122.3967177}, {"severity": "u'INJURY", "street1": "2NDST", "street2": "'MINNAST", "date": "u'20120718", "year": "2012", "lat": 37.7876012, "lng": -122.3993312}, {"severity": "u'INJURY", "street1": "2NDST", "street2": "'STILLMANST", "date": "u'20120720", "year": "2012", "lat": 37.7835245, "lng": -122.3941704}, {"severity": "u'INJURY", "street1": "37THAV", "street2": "'QUINTARAST", "date": "u'20120606", "year": "2012", "lat": 37.7477995, "lng": -122.4953671}, {"severity": "u'INJURY", "street1": "3RDST", "street2": "'MISSIONROCKRD", "date": "u'20120817", "year": "2012", "lat": 37.7729368, "lng": -122.3898089}, {"severity": "u'INJURY", "street1": "3RDST", "street2": "'STILLMANST", "date": "u'20120330", "year": "2012", "lat": 37.7817709, "lng": -122.3964107}, {"severity": "u'INJURY", "street1": "3RDST", "street2": "'VANDYKEAV", "date": "u'20120411", "year": "2012", "lat": 37.7292336, "lng": -122.3925655}, {"severity": "u'INJURY", "street1": "41STAV", "street2": "'KIRKHAMST", "date": "u'20120115", "year": "2012", "lat": 37.758803, "lng": -122.5004339}, {"severity": "u'INJURY", "street1": "4THAV", "street2": "'ANZAST", "date": "u'20120420", "year": "2012", "lat": 37.7791925, "lng": -122.462002}, {"severity": "u'INJURY", "street1": "4THST", "street2": "'FOLSOMST", "date": "u'20120116", "year": "2012", "lat": 37.7820607, "lng": -122.4011821}, {"severity": "u'INJURY", "street1": "4THST", "street2": "u'STEVENSON", "date": "u'20120427", "year": "2012", "lat": 37.7852826, "lng": -122.4052367}, {"severity": "u'INJURY", "street1": "5THST", "street2": "'BRANNANST", "date": "u'20120118", "year": "2012", "lat": 37.7765851, "lng": -122.398772}, {"severity": "u'INJURY", "street1": "5THST", "street2": "'FOLSOMST", "date": "u'20120606", "year": "2012", "lat": 37.7802841, "lng": -122.4034164}, {"severity": "u'INJURY", "street1": "5THST", "street2": "'HARRISONST", "date": "u'20120427", "year": "2012", "lat": 37.779049, "lng": -122.4018621}, {"severity": "u'INJURY", "street1": "6THST", "street2": "'FOLSOMST", "date": "u'20120729", "year": "2012", "lat": 37.7785241, "lng": -122.4056342}, {"severity": "u'INJURY", "street1": "7THAV", "street2": "'JUDAHST", "date": "u'20120118", "year": "2012", "lat": 37.7622695, "lng": -122.4640639}, {"severity": "u'INJURY", "street1": "7THST", "street2": "'BRANNANST", "date": "u'20120411", "year": "2012", "lat": 37.7730575, "lng": -122.4032376}, {"severity": "u'INJURY", "street1": "8THAV", "street2": "'LINCOLNAV", "date": "u'20120216", "year": "2012", "lat": 37.7660197, "lng": -122.4653809}, {"severity": "u'INJURY", "street1": "8THST", "street2": "'BRANNANST", "date": "u'20120629", "year": "2012", "lat": 37.7713302, "lng": -122.4054307}, {"severity": "u'INJURY", "street1": "8THST", "street2": "'BRYANTST", "date": "u'20120512", "year": "2012", "lat": 37.7725615, "lng": -122.4069632}, {"severity": "u'INJURY", "street1": "8THST", "street2": "'IRWINST", "date": "u'20120605", "year": "2012", "lat": 37.7666908, "lng": -122.3997197}, {"severity": "u'INJURY", "street1": "8THST", "street2": "'MISSIONST", "date": "u'20120519", "year": "2012", "lat": 37.7774649, "lng": -122.4131792}, {"severity": "u'INJURY", "street1": "8THST", "street2": "'MISSIONST", "date": "u'20120722", "year": "2012", "lat": 37.7774649, "lng": -122.4131792}, {"severity": "u'INJURY", "street1": "9THST", "street2": "'FOLSOMST", "date": "u'20120827", "year": "2012", "lat": 37.7737855, "lng": -122.4116385}, {"severity": "u'PDO", "street1": "9THST", "street2": "'MISSIONST", "date": "u'20120312", "year": "2012", "lat": 37.7762211, "lng": -122.4147406}, {"severity": "u'INJURY", "street1": "ALEMANY", "street2": "'CRESCENTAV", "date": "u'20120210", "year": "2012", "lat": 37.734785, "lng": -122.4108679}, {"severity": "u'INJURY", "street1": "ARGUELLOBL", "street2": "'GOLDENGATEAV", "date": "u'20120117", "year": "2012", "lat": 37.776179, "lng": -122.4584981}, {"severity": "u'INJURY", "street1": "ARGUELLOBL", "street2": "'MCALLISTERST", "date": "u'20120420", "year": "2012", "lat": 37.7752481, "lng": -122.4584281}, {"severity": "u'INJURY", "street1": "ARGUELLOBL", "street2": "'PRESIDIOTE", "date": "u'20120205", "year": "2012", "lat": 37.788405, "lng": -122.459388}, {"severity": "u'INJURY", "street1": "ARGUELLOST", "street2": "'GEARYBL", "date": "u'20120830", "year": "2012", "lat": 37.7813444, "lng": -122.4588752}, {"severity": "u'INJURY", "street1": "ASHBURYST", "street2": "'ASHBURYST80", "date": "u'20120630", "year": "2012", "lat": 37.773915, "lng": -122.436524}, {"severity": "u'PDO", "street1": "BAKERST", "street2": "'FELLST", "date": "u'20120424", "year": "2012", "lat": 37.7736412, "lng": -122.4409112}, {"severity": "u'INJURY", "street1": "BAYSHORE", "street2": "'BACONST", "date": "u'20120721", "year": "2012", "lat": 37.7279635, "lng": -122.4021642}, {"severity": "u'INJURY", "street1": "BAYST", "street2": "'HYDEST", "date": "u'20120325", "year": "2012", "lat": 37.8048154, "lng": -122.4201958}, {"severity": "u'INJURY", "street1": "BEACHST", "street2": "'GRANTAV", "date": "u'20120802", "year": "2012", "lat": 37.8081151, "lng": -122.4090985}, {"severity": "u'INJURY", "street1": "BOSWORTHST", "street2": "CUVIER", "date": "u'20120421", "year": "2012", "lat": 37.7334852, "lng": -122.4286003}, {"severity": "u'INJURY", "street1": "BRANNANST", "street2": "'2NDST", "date": "u'20120403", "year": "2012", "lat": 37.7818497, "lng": -122.3920993}, {"severity": "u'INJURY", "street1": "BRANNANST", "street2": "'4THST", "date": "u'20120515", "year": "2012", "lat": 37.778341, "lng": -122.3965525}, {"severity": "u'INJURY", "street1": "BROADWAY", "street2": "'FRONTST", "date": "u'20120816", "year": "2012", "lat": 37.7987416, "lng": -122.3998991}, {"severity": "u'INJURY", "street1": "BROADWAY", "street2": "STOCKTON", "date": "u'20120419", "year": "2012", "lat": 37.7976479, "lng": -122.4086392}, {"severity": "u'INJURY", "street1": "BROADWAYST", "street2": "'POLKST", "date": "u'20120518", "year": "2012", "lat": 37.7959845, "lng": -122.4217921}, {"severity": "u'INJURY", "street1": "BRYANTST", "street2": "'ALAMEDAST", "date": "u'20120206", "year": "2012", "lat": 37.7681764, "lng": -122.4107552}, {"severity": "u'INJURY", "street1": "BUCHANANST", "street2": "'PAGEST", "date": "u'20120818", "year": "2012", "lat": 37.7734778, "lng": -122.4273467}, {"severity": "u'PDO", "street1": "BUSHST", "street2": "'MONTGOMERYST", "date": "u'20120117", "year": "2012", "lat": 37.790976, "lng": -122.4024281}, {"severity": "u'INJURY", "street1": "CABRILLOST", "street2": "'16THAV", "date": "u'20120610", "year": "2012", "lat": 37.774876, "lng": -122.4747175}, {"severity": "u'INJURY", "street1": "CALIFORNIAST", "street2": "'17THAV", "date": "u'20120616", "year": "2012", "lat": 37.7842709, "lng": -122.4764544}, {"severity": "u'INJURY", "street1": "CALIFORNIAST", "street2": "'BRODERICKST", "date": "u'20120813", "year": "2012", "lat": 37.7878596, "lng": -122.44211}, {"severity": "u'INJURY", "street1": "CAPPST", "street2": "'22NDST", "date": "u'20120721", "year": "2012", "lat": 37.7555087, "lng": -122.4176652}, {"severity": "u'INJURY", "street1": "CASTROST", "street2": "'17THST", "date": "u'20120302", "year": "2012", "lat": 37.7627477, "lng": -122.4351586}, {"severity": "u'INJURY", "street1": "CESARCHAVEZ", "street2": "'HARRISONST", "date": "u'20120107", "year": "2012", "lat": 37.7482566, "lng": -122.411481}, {"severity": "u'INJURY", "street1": "CHENERYST", "street2": "'CHARLESST", "date": "u'20120322", "year": "2012", "lat": 37.7383545, "lng": -122.4261058}, {"severity": "u'INJURY", "street1": "CHINABA", "street2": "'3RDST", "date": "u'20120707", "year": "2012", "lat": 37.7793668, "lng": -122.3934134}, {"severity": "u'INJURY", "street1": "CLEMENTST", "street2": "'18THAV", "date": "u'20120131", "year": "2012", "lat": 37.7823567, "lng": -122.4773847}, {"severity": "u'INJURY", "street1": "CLEMENTST", "street2": "'6THAV", "date": "u'20120108", "year": "2012", "lat": 37.7829523, "lng": -122.4644277}, {"severity": "u'INJURY", "street1": "CLEMENTST", "street2": "'9THAV", "date": "u'20120705", "year": "2012", "lat": 37.7828017, "lng": -122.4676437}, {"severity": "u'INJURY", "street1": "COLEST", "street2": "'CARLST", "date": "u'20120119", "year": "2012", "lat": 37.76556, "lng": -122.44996}, {"severity": "u'INJURY", "street1": "COLUMBUSAV", "street2": "'CHESTNUTST", "date": "u'20120428", "year": "2012", "lat": 37.803794, "lng": -122.415136}, {"severity": "u'INJURY", "street1": "COLUMBUSAV", "street2": "'COLUMBUSAV", "date": "u'20120731", "year": "2012", "lat": 37.797267, "lng": -122.406098}, {"severity": "u'INJURY", "street1": "COLUMBUSAV", "street2": "'GREENWICHST", "date": "u'20120818", "year": "2012", "lat": 37.8019526, "lng": -122.412639}, {"severity": "u'INJURY", "street1": "CORTLANDAV", "street2": "'BRADFORDST", "date": "u'20120516", "year": "2012", "lat": 37.7397234, "lng": -122.4094832}, {"severity": "u'INJURY", "street1": "DIVISADEROST", "street2": "'PAGEST", "date": "u'20120501", "year": "2012", "lat": 37.7722232, "lng": -122.4371587}, {"severity": "u'PDO", "street1": "DIVISIONST", "street2": "'9THST", "date": "u'20120309", "year": "2012", "lat": 37.7694443, "lng": -122.4062321}, {"severity": "u'INJURY", "street1": "DIVISIONST", "street2": "'9THST", "date": "u'20120705", "year": "2012", "lat": 37.7694443, "lng": -122.4062321}, {"severity": "u'INJURY", "street1": "DOLORESST", "street2": "'15THST", "date": "u'20120116", "year": "2012", "lat": 37.7662724, "lng": -122.4264995}, {"severity": "u'INJURY", "street1": "DUBOCEAV", "street2": "'MISSIONST", "date": "u'20120626", "year": "2012", "lat": 37.7700039, "lng": -122.4178412}, {"severity": "u'INJURY", "street1": "ELLISST", "street2": "u'LEAVENWORTH", "date": "u'20120422", "year": "2012", "lat": 37.7846631, "lng": -122.4144723}, {"severity": "u'INJURY", "street1": "ELLISST", "street2": "'TAYLORST", "date": "u'20120201", "year": "2012", "lat": 37.7850798, "lng": -122.4111597}, {"severity": "u'INJURY", "street1": "THEEMBARCADERO", "street2": "'MISSIONST", "date": "u'20120814", "year": "2012", "lat": 37.7642386, "lng": -122.4196362}, {"severity": "u'INJURY", "street1": "THEEMBARCADERO", "street2": "DONCHEE", "date": "u'20120129", "year": "2012", "lat": 37.794105, "lng": -122.393874}, {"severity": "u'INJURY", "street1": "THEEMBARCADERO", "street2": "DONCHEE", "date": "u'20120203", "year": "2012", "lat": 37.794105, "lng": -122.393874}, {"severity": "u'INJURY", "street1": "THEEMBARCADERO", "street2": "'HARRISONBL", "date": "u'20120626", "year": "2012", "lat": 37.789524, "lng": -122.3886044}, {"severity": "u'INJURY", "street1": "EMBARCADEROST", "street2": "'BRANNANST", "date": "u'20120515", "year": "2012", "lat": 37.7803611, "lng": -122.3939557}, {"severity": "u'PDO", "street1": "EUREKAST", "street2": "'20THST", "date": "u'20120108", "year": "2012", "lat": 37.7574921, "lng": -122.4379429}, {"severity": "u'INJURY", "street1": "FELLST", "street2": "'BAKERST", "date": "u'20120522", "year": "2012", "lat": 37.7736412, "lng": -122.4409112}, {"severity": "u'INJURY", "street1": "FELLST", "street2": "'BRODERICKST", "date": "u'20120617", "year": "2012", "lat": 37.7738686, "lng": -122.4392751}, {"severity": "u'PDO", "street1": "FELLST", "street2": "'DIVISADEROST", "date": "u'20120107", "year": "2012", "lat": 37.7740721, "lng": -122.4376238}, {"severity": "u'INJURY", "street1": "FELLST", "street2": "'DIVISADEROST", "date": "u'20120214", "year": "2012", "lat": 37.7740721, "lng": -122.4376238}, {"severity": "u'INJURY", "street1": "FELLST", "street2": "'DIVISADEROST", "date": "u'20120215", "year": "2012", "lat": 37.7740721, "lng": -122.4376238}, {"severity": "u'INJURY", "street1": "FELLST", "street2": "'DIVISADEROST", "date": "u'20120406", "year": "2012", "lat": 37.7740721, "lng": -122.4376238}, {"severity": "u'INJURY", "street1": "FELLST", "street2": "'LYONST", "date": "u'20120126", "year": "2012", "lat": 37.7734303, "lng": -122.4425649}, {"severity": "u'INJURY", "street1": "FILLMOREST", "street2": "'CALIFORNIAST", "date": "u'20120605", "year": "2012", "lat": 37.7889131, "lng": -122.4338632}, {"severity": "u'INJURY", "street1": "FOLSOMST", "street2": "'14THST", "date": "u'20120607", "year": "2012", "lat": 37.7685432, "lng": -122.4156459}, {"severity": "u'INJURY", "street1": "FOLSOMST", "street2": "'6THST", "date": "u'20120713", "year": "2012", "lat": 37.7785241, "lng": -122.4056342}, {"severity": "u'INJURY", "street1": "FOLSOMST", "street2": "'6THST", "date": "u'20120810", "year": "2012", "lat": 37.7785241, "lng": -122.4056342}, {"severity": "u'INJURY", "street1": "FOLSOMST", "street2": "'HALLAMST", "date": "u'20120501", "year": "2012", "lat": 37.775947, "lng": -122.4088944}, {"severity": "u'FATAL", "street1": "FRANKLINST", "street2": "'OAKST", "date": "u'20120529", "year": "2012", "lat": 37.7752318, "lng": -122.420976}, {"severity": "u'INJURY", "street1": "FRANKLINST", "street2": "'PACIFICAV", "date": "u'20120812", "year": "2012", "lat": 37.794607, "lng": -122.4248841}, {"severity": "u'INJURY", "street1": "FRONTST", "street2": "'GREENST", "date": "u'20120621", "year": "2012", "lat": 37.8006271, "lng": -122.4002702}, {"severity": "u'INJURY", "street1": "FULTONST", "street2": "'ARGUELLOBL", "date": "u'20120103", "year": "2012", "lat": 37.774338, "lng": -122.458356}, {"severity": "u'INJURY", "street1": "FULTONST", "street2": "'BRODERICKST", "date": "u'20120118", "year": "2012", "lat": 37.7766543, "lng": -122.4398489}, {"severity": "u'INJURY", "street1": "FULTONST", "street2": "'CENTRALAV", "date": "u'20120828", "year": "2012", "lat": 37.7760211, "lng": -122.4447795}, {"severity": "u'INJURY", "street1": "FULTONST", "street2": "'CENTRALAV", "date": "u'20120828", "year": "2012", "lat": 37.7760211, "lng": -122.4447795}, {"severity": "u'INJURY", "street1": "GEARYBL", "street2": "'7THAV", "date": "u'20120608", "year": "2012", "lat": 37.7810375, "lng": -122.4653564}, {"severity": "u'INJURY", "street1": "GEARYBL", "street2": "'8THAV", "date": "u'20120521", "year": "2012", "lat": 37.7808603, "lng": -122.4664251}, {"severity": "u'INJURY", "street1": "GEARYBL", "street2": "u'DIVISADERO", "date": "u'20120718", "year": "2012", "lat": 37.7833959, "lng": -122.4394308}, {"severity": "u'INJURY", "street1": "GEARYBL", "street2": "'GRANTAV", "date": "u'20120301", "year": "2012", "lat": 37.7877706, "lng": -122.4051121}, {"severity": "u'INJURY", "street1": "GENEVAAV", "street2": "'BROOKDALEAV", "date": "u'20120227", "year": "2012", "lat": 37.7100883, "lng": -122.4245787}, {"severity": "u'INJURY", "street1": "GENEVAAV", "street2": "'PARISST", "date": "u'20120223", "year": "2012", "lat": 37.7156442, "lng": -122.4394706}, {"severity": "u'INJURY", "street1": "GENEVAAV", "street2": "'SANJOSEAV", "date": "u'20120620", "year": "2012", "lat": 37.7207581, "lng": -122.4465759}, {"severity": "u'INJURY", "street1": "GOLDENGATEBRIDGE", "street2": "'SCOTTST", "date": "u'20120712", "year": "2012", "lat": 37.7789495, "lng": -122.4368706}, {"severity": "u'INJURY", "street1": "GOLDENGATEBRIDGE", "street2": "'STEINERST", "date": "u'20120516", "year": "2012", "lat": 37.7793637, "lng": -122.433592}, {"severity": "u'INJURY", "street1": "GOUGH", "street2": "'PACIFICAV", "date": "u'20120308", "year": "2012", "lat": 37.7943931, "lng": -122.4265472}, {"severity": "u'INJURY", "street1": "GREATHIGHWAY", "street2": "'CUTLERST", "date": "u'20120128", "year": "2012", "lat": 37.7370173, "lng": -122.5063388}, {"severity": "u'INJURY", "street1": "GROVEST", "street2": "'FRANKLINST", "date": "u'20120201", "year": "2012", "lat": 37.7780313, "lng": -122.4215283}, {"severity": "u'INJURY", "street1": "GROVEST", "street2": "'LARKINST", "date": "u'20120311", "year": "2012", "lat": 37.7786757, "lng": -122.4166025}, {"severity": "u'INJURY", "street1": "GROVEST", "street2": "'LARKINST", "date": "u'20120324", "year": "2012", "lat": 37.7786757, "lng": -122.4166025}, {"severity": "u'INJURY", "street1": "GROVEST", "street2": "'VANNESSAV", "date": "u'20120719", "year": "2012", "lat": 37.7782859, "lng": -122.419828}, {"severity": "u'INJURY", "street1": "GUERREROST", "street2": "CESARCHAVEZ", "date": "u'20120614", "year": "2012", "lat": 37.7479746, "lng": -122.422421}, {"severity": "u'INJURY", "street1": "HAIGHTST", "street2": "'ASHBURYST", "date": "u'20120307", "year": "2012", "lat": 37.7700099, "lng": -122.4469365}, {"severity": "u'INJURY", "street1": "HAIGHTST", "street2": "'DIVISADEROST", "date": "u'20120217", "year": "2012", "lat": 37.7712749, "lng": -122.4371285}, {"severity": "u'INJURY", "street1": "HAIGHTST", "street2": "'DIVISADEROST", "date": "u'20120330", "year": "2012", "lat": 37.7712749, "lng": -122.4371285}, {"severity": "u'PDO", "street1": "HAIGHTST", "street2": "'LAGUNAST", "date": "u'20120324", "year": "2012", "lat": 37.7727315, "lng": -122.4255433}, {"severity": "u'INJURY", "street1": "HAIGHTST", "street2": "'SCOTTST", "date": "u'20120120", "year": "2012", "lat": 37.771487, "lng": -122.4353672}, {"severity": "u'INJURY", "street1": "HARRISONST", "street2": "'11THST", "date": "u'20120217", "year": "2012", "lat": 37.7706429, "lng": -122.4124994}, {"severity": "u'INJURY", "street1": "HARRISONST", "street2": "'12THST", "date": "u'20120214", "year": "2012", "lat": 37.7700744, "lng": -122.4130826}, {"severity": "u'INJURY", "street1": "HARRISONST", "street2": "'13THST", "date": "u'20120714", "year": "2012", "lat": 37.7696315, "lng": -122.413332}, {"severity": "u'INJURY", "street1": "HARRISONST", "street2": "'20THST", "date": "u'20120512", "year": "2012", "lat": 37.7590319, "lng": -122.4125147}, {"severity": "u'INJURY", "street1": "HARRISONST", "street2": "'20THST", "date": "u'20120729", "year": "2012", "lat": 37.7590319, "lng": -122.4125147}, {"severity": "u'INJURY", "street1": "HARRISONST", "street2": "'21STST", "date": "u'20120318", "year": "2012", "lat": 37.7574294, "lng": -122.4123656}, {"severity": "u'INJURY", "street1": "HARRISONST", "street2": "'21STST", "date": "u'20120419", "year": "2012", "lat": 37.7574294, "lng": -122.4123656}, {"severity": "u'INJURY", "street1": "HARRISONST", "street2": "'MARIPOSAST", "date": "u'20120507", "year": "2012", "lat": 37.7628873, "lng": -122.412899}, {"severity": "u'INJURY", "street1": "HYDEST", "street2": "'FULTONST", "date": "u'20120320", "year": "2012", "lat": 37.7798005, "lng": -122.4151553}, {"severity": "u'INJURY", "street1": "HYDEST", "street2": "'MARKETST", "date": "u'20120512", "year": "2012", "lat": 37.778542, "lng": -122.414813}, {"severity": "u'INJURY", "street1": "HYDEST", "street2": "'POSTST", "date": "u'20120226", "year": "2012", "lat": 37.78724, "lng": -122.41626}, {"severity": "u'INJURY", "street1": "IRVINGST", "street2": "'12THAV", "date": "u'20120113", "year": "2012", "lat": 37.7638988, "lng": -122.4695341}, {"severity": "u'INJURY", "street1": "IRVINGST", "street2": "'2NDAV", "date": "u'20120316", "year": "2012", "lat": 37.7643813, "lng": -122.4588124}, {"severity": "u'INJURY", "street1": "JACKSONST", "street2": "u'DRUMM", "date": "u'20120831", "year": "2012", "lat": 37.7972266, "lng": -122.3971684}, {"severity": "u'INJURY", "street1": "JEFFERSONST", "street2": "'MASONST", "date": "u'20120318", "year": "2012", "lat": 37.8084429, "lng": -122.4141848}, {"severity": "u'INJURY", "street1": "JONESST", "street2": "'EDDYST", "date": "u'20120531", "year": "2012", "lat": 37.7839385, "lng": -122.4126255}, {"severity": "u'INJURY", "street1": "KEZARDR", "street2": "LINCOLN", "date": "u'20120523", "year": "2012", "lat": 37.7661683, "lng": -122.4604571}, {"severity": "u'INJURY", "street1": "KINGST", "street2": "'3RDST", "date": "u'20120601", "year": "2012", "lat": 37.7780083, "lng": -122.3917215}, {"severity": "u'INJURY", "street1": "KINGST", "street2": "'3RDST", "date": "u'20120725", "year": "2012", "lat": 37.7780083, "lng": -122.3917215}, {"severity": "u'INJURY", "street1": "KINGST", "street2": "'4THST", "date": "u'20120625", "year": "2012", "lat": 37.7764938, "lng": -122.3940593}, {"severity": "u'INJURY", "street1": "LAGUNAST", "street2": "'HAIGHTST", "date": "u'20120520", "year": "2012", "lat": 37.7727315, "lng": -122.4255433}, {"severity": "u'INJURY", "street1": "LAKEMERCED", "street2": "'JOHNMUIRDR", "date": "u'20120628", "year": "2012", "lat": 37.7085827, "lng": -122.4867355}, {"severity": "u'INJURY", "street1": "LYONST", "street2": "'FULTONST", "date": "u'20120611", "year": "2012", "lat": 37.7762287, "lng": -122.4431343}, {"severity": "u'INJURY", "street1": "MARKETST", "street2": "'3RDST", "date": "u'20120125", "year": "2012", "lat": 37.7876655, "lng": -122.4034605}, {"severity": "u'INJURY", "street1": "MARKETST", "street2": "'3RDST", "date": "u'20120306", "year": "2012", "lat": 37.7876655, "lng": -122.4034605}, {"severity": "u'INJURY", "street1": "MARKETST", "street2": "'3RDST", "date": "u'20120404", "year": "2012", "lat": 37.7876655, "lng": -122.4034605}, {"severity": "u'INJURY", "street1": "MARKETST", "street2": "'3RDST", "date": "u'20120702", "year": "2012", "lat": 37.7876655, "lng": -122.4034605}, {"severity": "u'INJURY", "street1": "MARKETST", "street2": "'5THST", "date": "u'20120604", "year": "2012", "lat": 37.7840081, "lng": -122.408092}, {"severity": "u'INJURY", "street1": "MARKETST", "street2": "'5THST", "date": "u'20120619", "year": "2012", "lat": 37.7840081, "lng": -122.408092}, {"severity": "u'INJURY", "street1": "MARKETST", "street2": "'7THST", "date": "u'20120828", "year": "2012", "lat": 37.7804664, "lng": -122.4125602}, {"severity": "u'INJURY", "street1": "MARKETST", "street2": "'8THST", "date": "u'20120502", "year": "2012", "lat": 37.778542, "lng": -122.414813}, {"severity": "u'INJURY", "street1": "MARKETST", "street2": "'CHURCHST", "date": "u'20120409", "year": "2012", "lat": 37.7675884, "lng": -122.4289385}, {"severity": "u'INJURY", "street1": "MARKETST", "street2": "u'GOUGH", "date": "u'20120807", "year": "2012", "lat": 37.7730845, "lng": -122.4220455}, {"severity": "u'INJURY", "street1": "MARKETST", "street2": "'GOUGHST", "date": "u'20120214", "year": "2012", "lat": 37.7730845, "lng": -122.4220455}, {"severity": "u'INJURY", "street1": "MARKETST", "street2": "'GOUGHST", "date": "u'20120728", "year": "2012", "lat": 37.7730845, "lng": -122.4220455}, {"severity": "u'INJURY", "street1": "MARKETST", "street2": "'GUERREROST", "date": "u'20120307", "year": "2012", "lat": 37.7707539, "lng": -122.4247672}, {"severity": "u'INJURY", "street1": "MARKETST", "street2": "'GUERREROST", "date": "u'20120629", "year": "2012", "lat": 37.7707539, "lng": -122.4247672}, {"severity": "u'INJURY", "street1": "MARKETST", "street2": "'OCTAVIAST", "date": "u'20120605", "year": "2012", "lat": 37.7717843, "lng": -122.4236948}, {"severity": "u'INJURY", "street1": "MARKETST", "street2": "'OCTAVIAST", "date": "u'20120807", "year": "2012", "lat": 37.7717843, "lng": -122.4236948}, {"severity": "u'INJURY", "street1": "MARKETST", "street2": "'STEUARTST", "date": "u'20120103", "year": "2012", "lat": 37.7944889, "lng": -122.3948012}, {"severity": "u'INJURY", "street1": "MARKETST", "street2": "'VALENCIAST", "date": "u'20120105", "year": "2012", "lat": 37.7725376, "lng": -122.4227233}, {"severity": "u'INJURY", "street1": "MARKETST", "street2": "'VALENCIAST", "date": "u'20120609", "year": "2012", "lat": 37.7725376, "lng": -122.4227233}, {"severity": "u'INJURY", "street1": "MARKETST", "street2": "'VALENCIAST", "date": "u'20120816", "year": "2012", "lat": 37.7725376, "lng": -122.4227233}, {"severity": "u'INJURY", "street1": "MARKETST", "street2": "'VALENCIAST", "date": "u'20120824", "year": "2012", "lat": 37.7725376, "lng": -122.4227233}, {"severity": "u'INJURY", "street1": "MARKETST", "street2": "'VANNESSAV", "date": "u'20120821", "year": "2012", "lat": 37.7752057, "lng": -122.4192085}, {"severity": "u'INJURY", "street1": "MASONST", "street2": "'BROADWAYST", "date": "u'20120820", "year": "2012", "lat": 37.7972835, "lng": -122.4119693}, {"severity": "u'INJURY", "street1": "MASONST", "street2": "'CHESTNUTST", "date": "u'20120723", "year": "2012", "lat": 37.8037856, "lng": -122.4132525}, {"severity": "u'INJURY", "street1": "MASONST", "street2": "'POSTST", "date": "u'20120316", "year": "2012", "lat": 37.7881097, "lng": -122.4100714}, {"severity": "u'INJURY", "street1": "MASONICAV", "street2": "'EWINGRD", "date": "u'20120722", "year": "2012", "lat": 37.7801822, "lng": -122.447312}, {"severity": "u'INJURY", "street1": "MCALLISTERST", "street2": "'VANNESSAV", "date": "u'20120303", "year": "2012", "lat": 37.7800871, "lng": -122.4201816}, {"severity": "u'INJURY", "street1": "MCALLISTERST", "street2": "'VANNESSAV", "date": "u'20120731", "year": "2012", "lat": 37.7800871, "lng": -122.4201816}, {"severity": "u'INJURY", "street1": "MINNAST", "street2": "'11THST", "date": "u'20120119", "year": "2012", "lat": 37.7739126, "lng": -122.416596}, {"severity": "u'INJURY", "street1": "MISSION", "street2": "'16THST", "date": "u'20120412", "year": "2012", "lat": 37.765053, "lng": -122.4197149}, {"severity": "u'INJURY", "street1": "MISSION", "street2": "'17THST", "date": "u'20120624", "year": "2012", "lat": 37.7634242, "lng": -122.4195575}, {"severity": "u'INJURY", "street1": "MISSION", "street2": "'18THST", "date": "u'20120123", "year": "2012", "lat": 37.7618402, "lng": -122.4194024}, {"severity": "u'INJURY", "street1": "MISSION", "street2": "'22NDST", "date": "u'20120406", "year": "2012", "lat": 37.7554469, "lng": -122.4187748}, {"severity": "u'PDO", "street1": "MISSION", "street2": "'6THST", "date": "u'20120112", "year": "2012", "lat": 37.7809857, "lng": -122.4087183}, {"severity": "u'INJURY", "street1": "MISSION", "street2": "'9THST", "date": "u'20120507", "year": "2012", "lat": 37.7762211, "lng": -122.4147406}, {"severity": "u'PDO", "street1": "MISSION", "street2": "CESARCHAVEZ", "date": "u'20120118", "year": "2012", "lat": 37.7481117, "lng": -122.4182746}, {"severity": "u'INJURY", "street1": "MISSION", "street2": "'CORTLANDAV", "date": "u'20120617", "year": "2012", "lat": 37.7410379, "lng": -122.4228308}, {"severity": "u'PDO", "street1": "MISSION", "street2": "'EUGENIAAV", "date": "u'20120422", "year": "2012", "lat": 37.7422213, "lng": -122.4220772}, {"severity": "u'INJURY", "street1": "MISSION", "street2": "'FARRAGUTAV", "date": "u'20120402", "year": "2012", "lat": 37.709959, "lng": -122.449354}, {"severity": "u'INJURY", "street1": "MISSION", "street2": "'FARRAGUTAV", "date": "u'20120421", "year": "2012", "lat": 37.709959, "lng": -122.449354}, {"severity": "u'INJURY", "street1": "MISSION", "street2": "'ITALYAV", "date": "u'20120427", "year": "2012", "lat": 37.718502, "lng": -122.4395281}, {"severity": "u'INJURY", "street1": "MISSION", "street2": "'MAYNARDST", "date": "u'20120217", "year": "2012", "lat": 37.7292307, "lng": -122.4308447}, {"severity": "u'INJURY", "street1": "MISSION", "street2": "'OLIVERST", "date": "u'20120503", "year": "2012", "lat": 37.7095608, "lng": -122.4505181}, {"severity": "u'INJURY", "street1": "MISSION", "street2": "'OLIVERST", "date": "u'20120531", "year": "2012", "lat": 37.7095608, "lng": -122.4505181}, {"severity": "u'INJURY", "street1": "MISSION", "street2": "'ONONDAGAAV", "date": "u'20120305", "year": "2012", "lat": 37.7211772, "lng": -122.4374998}, {"severity": "u'INJURY", "street1": "MISSION", "street2": "'SANJUANAV", "date": "u'20120109", "year": "2012", "lat": 37.7240048, "lng": -122.4353196}, {"severity": "u'INJURY", "street1": "MISSION", "street2": "'SENECAAV", "date": "u'20120609", "year": "2012", "lat": 37.7176754, "lng": -122.4401492}, {"severity": "u'INJURY", "street1": "MISSION", "street2": "'THERESAST", "date": "u'20120130", "year": "2012", "lat": 37.7276495, "lng": -122.4324302}, {"severity": "u'INJURY", "street1": "MISSION", "street2": "'VIRGINIAST", "date": "u'20120811", "year": "2012", "lat": 37.7431247, "lng": -122.4214908}, {"severity": "u'INJURY", "street1": "NIAGARAAV", "street2": "'SANJOSEAV", "date": "u'20120718", "year": "2012", "lat": 37.71948, "lng": -122.4476258}, {"severity": "u'PDO", "street1": "NOEST", "street2": "'15THST", "date": "u'20121116", "year": "2012", "lat": 37.7658768, "lng": -122.4332402}, {"severity": "u'INJURY", "street1": "NORIEGAST", "street2": "'46THAV", "date": "u'20120423", "year": "2012", "lat": 37.7529849, "lng": -122.5054124}, {"severity": "u'INJURY", "street1": "NORLTHPOINTST", "street2": "'POLKST", "date": "u'20120304", "year": "2012", "lat": 37.8053079, "lng": -122.4236801}, {"severity": "u'INJURY", "street1": "NORTHPOINTST", "street2": "'JONESST", "date": "u'20120210", "year": "2012", "lat": 37.8061684, "lng": -122.4170939}, {"severity": "u'INJURY", "street1": "NORTHPOINTST", "street2": "u'LEAVENWORTH", "date": "u'20120312", "year": "2012", "lat": 37.8059434, "lng": -122.4187653}, {"severity": "u'INJURY", "street1": "OAKST", "street2": "'BRODERICKST", "date": "u'20120607", "year": "2012", "lat": 37.7729273, "lng": -122.4390897}, {"severity": "u'INJURY", "street1": "OAKST", "street2": "'DIVISADEROST", "date": "u'20120402", "year": "2012", "lat": 37.7731321, "lng": -122.4374385}, {"severity": "u'INJURY", "street1": "OAKST", "street2": "'DIVISADEROST", "date": "u'20120623", "year": "2012", "lat": 37.7731321, "lng": -122.4374385}, {"severity": "u'INJURY", "street1": "OAKST", "street2": "'SCOTTST", "date": "u'20120421", "year": "2012", "lat": 37.7733533, "lng": -122.4357496}, {"severity": "u'INJURY", "street1": "OCEANAV", "street2": "'FAXONAV", "date": "u'20120720", "year": "2012", "lat": 37.7247017, "lng": -122.459989}, {"severity": "u'INJURY", "street1": "OCEANAV", "street2": "'HAROLDAV", "date": "u'20120321", "year": "2012", "lat": 37.7232099, "lng": -122.4531372}, {"severity": "u'INJURY", "street1": "OCEANAV", "street2": "'HOWTHST", "date": "u'20120626", "year": "2012", "lat": 37.7230347, "lng": -122.4496335}, {"severity": "u'INJURY", "street1": "OCEANAV", "street2": "'VICTORIAST", "date": "u'20120218", "year": "2012", "lat": 37.7260346, "lng": -122.4642215}, {"severity": "u'INJURY", "street1": "PACIFICAV", "street2": "'FILLMOREST", "date": "u'20120731", "year": "2012", "lat": 37.7933533, "lng": -122.4346951}, {"severity": "u'INJURY", "street1": "PAGE", "street2": "'BUCHANANST", "date": "u'20120202", "year": "2012", "lat": 37.7734778, "lng": -122.4273467}, {"severity": "u'INJURY", "street1": "PAGE", "street2": "'CENTRALAV", "date": "u'20120811", "year": "2012", "lat": 37.7713688, "lng": -122.4438275}, {"severity": "u'INJURY", "street1": "PAGE", "street2": "'CLAYTONST", "date": "u'20120427", "year": "2012", "lat": 37.7707389, "lng": -122.4487556}, {"severity": "u'INJURY", "street1": "PAGE", "street2": "'SCOTTST", "date": "u'20120101", "year": "2012", "lat": 37.772424, "lng": -122.435558}, {"severity": "u'INJURY", "street1": "PARNASSUSAV", "street2": "'SHRADERST", "date": "u'20120711", "year": "2012", "lat": 37.7646915, "lng": -122.451221}, {"severity": "u'INJURY", "street1": "PAUL", "street2": "'BAYSHOREBL", "date": "u'20120822", "year": "2012", "lat": 37.7236223, "lng": -122.400783}, {"severity": "u'INJURY", "street1": "PHELPSST", "street2": "'CARROLLAV", "date": "u'20120105", "year": "2012", "lat": 37.7292077, "lng": -122.4008435}, {"severity": "u'INJURY", "street1": "PHELPSST", "street2": "'JERROLDAV", "date": "u'20120826", "year": "2012", "lat": 37.7398591, "lng": -122.3912753}, {"severity": "u'INJURY", "street1": "PINEST", "street2": "'POLKST", "date": "u'20120822", "year": "2012", "lat": 37.7896487, "lng": -122.4205116}, {"severity": "u'INJURY", "street1": "POLKST", "street2": "'CEDARST", "date": "u'20120415", "year": "2012", "lat": 37.786392, "lng": -122.4198492}, {"severity": "u'INJURY", "street1": "POLKST", "street2": "'CHESTNUTST", "date": "u'20120522", "year": "2012", "lat": 37.8025005, "lng": -122.4230936}, {"severity": "u'INJURY", "street1": "POLKST", "street2": "'PINEST", "date": "u'20120127", "year": "2012", "lat": 37.7896487, "lng": -122.4205116}, {"severity": "u'INJURY", "street1": "POLKST", "street2": "'PINEST", "date": "u'20120722", "year": "2012", "lat": 37.7896487, "lng": -122.4205116}, {"severity": "u'INJURY", "street1": "POLKST", "street2": "'TURKST", "date": "u'20120306", "year": "2012", "lat": 37.7821707, "lng": -122.4190036}, {"severity": "u'INJURY", "street1": "POLKST", "street2": "'TURKST", "date": "u'20120606", "year": "2012", "lat": 37.7821707, "lng": -122.4190036}, {"severity": "u'INJURY", "street1": "POLKST", "street2": "'VALLEJOST", "date": "u'20120511", "year": "2012", "lat": 37.7968993, "lng": -122.4219879}, {"severity": "u'INJURY", "street1": "POSTST", "street2": "u'LEAVENWORTH", "date": "u'20120716", "year": "2012", "lat": 37.7874653, "lng": -122.4149854}, {"severity": "u'INJURY", "street1": "POSTST", "street2": "'MASONST", "date": "u'20120301", "year": "2012", "lat": 37.7881097, "lng": -122.4100714}, {"severity": "u'INJURY", "street1": "POSTST", "street2": "'SCOTTST", "date": "u'20120508", "year": "2012", "lat": 37.7845329, "lng": -122.4380144}, {"severity": "u'INJURY", "street1": "POSTST", "street2": "'SCOTTST", "date": "u'20120717", "year": "2012", "lat": 37.7845329, "lng": -122.4380144}, {"severity": "u'INJURY", "street1": "POTREROAV", "street2": "'24THST", "date": "u'20120227", "year": "2012", "lat": 37.7529898, "lng": -122.4064139}, {"severity": "u'INJURY", "street1": "POTREROAV", "street2": "'25THST", "date": "u'20120111", "year": "2012", "lat": 37.7517318, "lng": -122.406148}, {"severity": "u'INJURY", "street1": "POTREROST", "street2": "'25THST", "date": "u'20120606", "year": "2012", "lat": 37.7517318, "lng": -122.406148}, {"severity": "u'INJURY", "street1": "VANNESS", "street2": "'21STST", "date": "u'20120306", "year": "2012", "lat": 37.7571755, "lng": -122.4167521}, {"severity": "u'INJURY", "street1": "SACRAMENTOST", "street2": "'LOCUSTST", "date": "u'20120106", "year": "2012", "lat": 37.7875555, "lng": -122.4519593}, {"severity": "u'INJURY", "street1": "SANJOSE", "street2": "'30THST", "date": "u'20120320", "year": "2012", "lat": 37.7422964, "lng": -122.4232184}, {"severity": "u'INJURY", "street1": "SANJOSE", "street2": "'LAKEVIEWAV", "date": "u'20120126", "year": "2012", "lat": 37.7161911, "lng": -122.450411}, {"severity": "u'INJURY", "street1": "SANJOSE", "street2": "'MONTEREYBL", "date": "u'20120731", "year": "2012", "lat": 37.732276, "lng": -122.4341322}, {"severity": "u'INJURY", "street1": "SANJOSE", "street2": "'SAGAMOREST", "date": "u'20120109", "year": "2012", "lat": 37.7114911, "lng": -122.4556034}, {"severity": "u'INJURY", "street1": "SANCHESST", "street2": "'15THST", "date": "u'20120127", "year": "2012", "lat": 37.7660087, "lng": -122.4310357}, {"severity": "u'INJURY", "street1": "SANCHEZST", "street2": "'HENRYST", "date": "u'20120607", "year": "2012", "lat": 37.7667981, "lng": -122.4310943}, {"severity": "u'INJURY", "street1": "SLOATBL", "street2": "'37THAV", "date": "u'20120603", "year": "2012", "lat": 37.7339679, "lng": -122.4944156}, {"severity": "u'INJURY", "street1": "SOUTHVA", "street2": "'23RDST", "date": "u'20120202", "year": "2012", "lat": 37.75417, "lng": -122.4131527}, {"severity": "u'INJURY", "street1": "SOUTHVA", "street2": "'24THST", "date": "u'20120525", "year": "2012", "lat": 37.7525524, "lng": -122.4132704}, {"severity": "u'INJURY", "street1": "STEINERST", "street2": "'GOLDENGATEAV", "date": "u'20120518", "year": "2012", "lat": 37.7793637, "lng": -122.433592}, {"severity": "u'INJURY", "street1": "STEINERST", "street2": "'SUTTERST", "date": "u'20120223", "year": "2012", "lat": 37.7858792, "lng": -122.4348875}, {"severity": "u'INJURY", "street1": "SUTTERST", "street2": "'LARKINST", "date": "u'20120221", "year": "2012", "lat": 37.7879902, "lng": -122.4185029}, {"severity": "u'INJURY", "street1": "TAYLORST", "street2": "'ELLISST", "date": "u'20120615", "year": "2012", "lat": 37.7850798, "lng": -122.4111597}, {"severity": "u'INJURY", "street1": "TAYLORST", "street2": "'TURKST", "date": "u'20120503", "year": "2012", "lat": 37.7832142, "lng": -122.4107842}, {"severity": "u'INJURY", "street1": "TERRYFR", "street2": "'SOUTHST", "date": "u'20120718", "year": "2012", "lat": 37.7690145, "lng": -122.3862964}, {"severity": "u'INJURY", "street1": "THEEMBARCADERO", "street2": "'GRANTAV", "date": "u'20120504", "year": "2012", "lat": 37.8081151, "lng": -122.4090985}, {"severity": "u'INJURY", "street1": "THEEMBARCADERO", "street2": "'MARKETST", "date": "u'20121028", "year": "2012", "lat": 37.7944731, "lng": -122.3948775}, {"severity": "u'INJURY", "street1": "TOWNSENDST", "street2": "'2NDST", "date": "u'20120124", "year": "2012", "lat": 37.7806303, "lng": -122.3905427}, {"severity": "u'INJURY", "street1": "TOWNSENDST", "street2": "'DIVISIONST", "date": "u'20120322", "year": "2012", "lat": 37.769894, "lng": -122.403301}, {"severity": "u'INJURY", "street1": "TREATST", "street2": "'22NDST", "date": "u'20120304", "year": "2012", "lat": 37.755769, "lng": -122.4132978}, {"severity": "u'INJURY", "street1": "TURKST", "street2": "'MASONST", "date": "u'20120823", "year": "2012", "lat": 37.7834308, "lng": -122.4091512}, {"severity": "u'INJURY", "street1": "TURKST", "street2": "'POLKST", "date": "u'20120419", "year": "2012", "lat": 37.7821707, "lng": -122.4190036}, {"severity": "u'INJURY", "street1": "TWINPEAKS", "street2": "'GRAYSTONETE", "date": "u'20120417", "year": "2012", "lat": 37.7594495, "lng": -122.447336}, {"severity": "u'INJURY", "street1": "ULLOAST", "street2": "'21STAV", "date": "u'20120312", "year": "2012", "lat": 37.7410921, "lng": -122.4777116}, {"severity": "u'INJURY", "street1": "VALENCIA", "street2": "u'SYCAMORE", "date": "u'20120217", "year": "2012", "lat": 37.7625788, "lng": -122.4216856}, {"severity": "u'INJURY", "street1": "VALENCIAST", "street2": "'14THST", "date": "u'20120115", "year": "2012", "lat": 37.7681528, "lng": -122.4222248}, {"severity": "u'INJURY", "street1": "VALENCIAST", "street2": "'14THST", "date": "u'20120606", "year": "2012", "lat": 37.7681528, "lng": -122.4222248}, {"severity": "u'INJURY", "street1": "VALENCIAST", "street2": "'15THST", "date": "u'20120326", "year": "2012", "lat": 37.7665431, "lng": -122.4220576}, {"severity": "u'INJURY", "street1": "VALENCIAST", "street2": "'17THST", "date": "u'20120316", "year": "2012", "lat": 37.7632962, "lng": -122.421752}, {"severity": "u'INJURY", "street1": "VALENCIAST", "street2": "'20THST", "date": "u'20120210", "year": "2012", "lat": 37.7584974, "lng": -122.4212866}, {"severity": "u'INJURY", "street1": "VALENCIAST", "street2": "'20THST", "date": "u'20120420", "year": "2012", "lat": 37.7584974, "lng": -122.4212866}, {"severity": "u'INJURY", "street1": "VALENCIAST", "street2": "'20THST", "date": "u'20120726", "year": "2012", "lat": 37.7584974, "lng": -122.4212866}, {"severity": "u'INJURY", "street1": "VALENCIAST", "street2": "'21STST", "date": "u'20120219", "year": "2012", "lat": 37.7568988, "lng": -122.4211319}, {"severity": "u'INJURY", "street1": "VALENCIAST", "street2": "'26THST", "date": "u'20120414", "year": "2012", "lat": 37.7489079, "lng": -122.4203495}, {"severity": "u'INJURY", "street1": "VALENCIAST", "street2": "u'DUBOCE", "date": "u'20120223", "year": "2012", "lat": 37.7698675, "lng": -122.4223893}, {"severity": "u'INJURY", "street1": "VALENCIAST", "street2": "'SYCAMOREST", "date": "u'20120829", "year": "2012", "lat": 37.7625788, "lng": -122.4216856}, {"severity": "u'INJURY", "street1": "VANNESS", "street2": "'MARKETST", "date": "u'20120513", "year": "2012", "lat": 37.775056, "lng": -122.419321}, {"severity": "u'INJURY", "street1": "VANNESS", "street2": "'POSTST", "date": "u'20120510", "year": "2012", "lat": 37.7866489, "lng": -122.4215008}, {"severity": "u'INJURY", "street1": "VERMONTST", "street2": "'17THST", "date": "u'20120301", "year": "2012", "lat": 37.7646778, "lng": -122.4045215}, {"severity": "u'INJURY", "street1": "WEBSTERST", "street2": "'GEARYBL", "date": "u'20120716", "year": "2012", "lat": 37.7845195, "lng": -122.4312314}, {"severity": "u'INJURY", "street1": "WEBSTERST", "street2": "'HAYESST", "date": "u'20120723", "year": "2012", "lat": 37.7760469, "lng": -122.4295518}, {"severity": "u'INJURY", "street1": "WEBSTERST", "street2": "'HICKORYST", "date": "u'20120204", "year": "2012", "lat": 37.7746514, "lng": -122.4292685}, {"severity": "u'INJURY", "street1": "WEBSTERST", "street2": "'TURKST", "date": "u'20120215", "year": "2012", "lat": 37.7807142, "lng": -122.4304707}, {"severity": "u'INJURY", "street1": "YORKST", "street2": "'22NDST", "date": "u'20120422", "year": "2012", "lat": 37.7560549, "lng": -122.4085016}]}, "clusters": {"2012": {"'FRANKLINST": [["37.7780313", "-122.4215283"]], "CALIFORNIAST": [["37.7842709", "-122.4764544"], ["37.7878596", "-122.4421100"]], "'ANZAST": [["37.7781536", "-122.4845547"]], "'HAIGHTST": [["37.7727315", "-122.4255433"]], "'MINNAST": [["37.7876012", "-122.3993312"]], "'FRONTST": [["37.7987416", "-122.3998991"]], "CABRILLOST": [["37.7748760", "-122.4747175"]], "NORTHPOINTST": [["37.8061684", "-122.4170939"], ["37.8059434", "-122.4187653"]], "DONCHEE": [["37.7941050", "-122.3938740"]], "PAGE": [["37.7734778", "-122.4273467"], ["37.7713688", "-122.4438275"], ["37.7707389", "-122.4487556"], ["37.7724240", "-122.4355580"]], "STEINERST": [["37.7793637", "-122.4335920"], ["37.7858792", "-122.4348875"]], "GROVEST": [["37.7780313", "-122.4215283"], ["37.7786757", "-122.4166025"], ["37.7786757", "-122.4166025"], ["37.7782859", "-122.4198280"]], "GENEVAAV": [["37.7100883", "-122.4245787"], ["37.7156442", "-122.4394706"], ["37.7207581", "-122.4465759"]], "BROADWAYST": [["37.7959845", "-122.4217921"]], "PARNASSUSAV": [["37.7646915", "-122.4512210"]], "14THST": [["37.7677354", "-122.4289483"], ["37.7680039", "-122.4244975"], ["37.7679538", "-122.4253988"], ["37.7684817", "-122.4167110"], ["37.7684217", "-122.4178218"], ["37.7681528", "-122.4222248"]], "u'DIVISADERO": [["37.7833959", "-122.4394308"]], "'14THST": [["37.7685432", "-122.4156459"]], "GUERREROST": [["37.7479746", "-122.4224210"]], "BAKERST": [["37.7736412", "-122.4409112"]], "'MASONST": [["37.8084429", "-122.4141848"]], "'21STST": [["37.7574294", "-122.4123656"]], "'BARTLETTST": [["37.7569690", "-122.4200110"]], "NORIEGAST": [["37.7529849", "-122.5054124"]], "u'STEVENSON": [["37.7852826", "-122.4052367"]], "'SANJOSEAV": [["37.7552793", "-122.4214569"]], "ULLOAST": [["37.7410921", "-122.4777116"]], "'25THST": [["37.7517318", "-122.4061480"]], "'GOUGHST": [["37.7730845", "-122.4220455"]], "THEEMBARCADERO": [["37.7642386", "-122.4196362"], ["37.7941050", "-122.3938740"], ["37.7941050", "-122.3938740"], ["37.7895240", "-122.3886044"], ["37.8081151", "-122.4090985"], ["37.7944731", "-122.3948775"]], "'18THST": [["37.7618402", "-122.4194024"]], "'RAMONAAV": [["37.7679538", "-122.4253988"]], "IRVINGST": [["37.7638988", "-122.4695341"], ["37.7643813", "-122.4588124"]], "'FAXONAV": [["37.7247017", "-122.4599890"]], "MINNAST": [["37.7739126", "-122.4165960"]], "12THAV": [["37.7732078", "-122.4701694"]], "LAGUNAST": [["37.7727315", "-122.4255433"]], "'12THAV": [["37.7638988", "-122.4695341"]], "'ARGUELLOBL": [["37.7743380", "-122.4583560"]], "JEFFERSONST": [["37.8084429", "-122.4141848"]], "KEZARDR": [["37.7661683", "-122.4604571"]], "'ONONDAGAAV": [["37.7211772", "-122.4374998"]], "'FELLST": [["37.7736412", "-122.4409112"]], "'13THST": [["37.7696315", "-122.4133320"]], "'GREENWICHST": [["37.8019526", "-122.4126390"]], "COLEST": [["37.7655600", "-122.4499600"]], "PACIFICAV": [["37.7933533", "-122.4346951"]], "'HAYESST": [["37.7760469", "-122.4295518"]], "u'DUBOCE": [["37.7698675", "-122.4223893"]], "'26THST": [["37.7489079", "-122.4203495"]], "'3RDST": [["37.7793668", "-122.3934134"]], "20THAV": [["37.7597955", "-122.4779532"]], "FRONTST": [["37.8006271", "-122.4002702"]], "13THST": [["37.7696315", "-122.4133320"], ["37.7696315", "-122.4133320"], ["37.7697121", "-122.4178256"]], "'7THAV": [["37.7810375", "-122.4653564"]], "'BUCHANANST": [["37.7734778", "-122.4273467"]], "'GREENST": [["37.8006271", "-122.4002702"]], "'SOUTHST": [["37.7690145", "-122.3862964"]], "'IRWINST": [["37.7666908", "-122.3997197"]], "CLEMENTST": [["37.7823567", "-122.4773847"], ["37.7829523", "-122.4644277"], ["37.7828017", "-122.4676437"]], "EMBARCADEROST": [["37.7803611", "-122.3939557"]], "FOLSOMST": [["37.7685432", "-122.4156459"], ["37.7785241", "-122.4056342"], ["37.7785241", "-122.4056342"], ["37.7759470", "-122.4088944"]], "'HALLAMST": [["37.7759470", "-122.4088944"]], "CESARCHAVEZ": [["37.7482566", "-122.4114810"]], "'VICTORIAST": [["37.7260346", "-122.4642215"]], "POTREROAV": [["37.7529898", "-122.4064139"], ["37.7517318", "-122.4061480"]], "VALENCIAST": [["37.7681528", "-122.4222248"], ["37.7681528", "-122.4222248"], ["37.7665431", "-122.4220576"], ["37.7632962", "-122.4217520"], ["37.7584974", "-122.4212866"], ["37.7584974", "-122.4212866"], ["37.7584974", "-122.4212866"], ["37.7568988", "-122.4211319"], ["37.7489079", "-122.4203495"], ["37.7698675", "-122.4223893"], ["37.7625788", "-122.4216856"]], "37THAV": [["37.7477995", "-122.4953671"]], "'22NDST": [["37.7555087", "-122.4176652"]], "'JERROLDAV": [["37.7398591", "-122.3912753"]], "16THST": [["37.7655043", "-122.4124415"], ["37.7648602", "-122.4228830"], ["37.7656180", "-122.4105284"], ["37.7651267", "-122.4186097"], ["37.7653296", "-122.4153468"], ["37.7666137", "-122.3952032"], ["37.7649612", "-122.4212475"]], "FILLMOREST": [["37.7889131", "-122.4338632"]], "'CRESCENTAV": [["37.7347850", "-122.4108679"]], "'BACONST": [["37.7279635", "-122.4021642"]], "'HARRISONST": [["37.7696315", "-122.4133320"]], "'HATTIEST": [["37.7605308", "-122.4409180"]], "BRANNANST": [["37.7818497", "-122.3920993"], ["37.7783410", "-122.3965525"]], "CHINABA": [["37.7793668", "-122.3934134"]], "'OLIVERST": [["37.7095608", "-122.4505181"]], "'SANJUANAV": [["37.7240048", "-122.4353196"]], "VERMONTST": [["37.7646778", "-122.4045215"]], "'PACIFICAV": [["37.7946070", "-122.4248841"]], "22NDST": [["37.7552793", "-122.4214569"]], "'SUTTERST": [["37.7858792", "-122.4348875"]], "'11THST": [["37.7706429", "-122.4124994"]], "'CLAYTONST": [["37.7707389", "-122.4487556"]], "'TURKST": [["37.7821707", "-122.4190036"]], "6THST": [["37.7785241", "-122.4056342"]], "NIAGARAAV": [["37.7194800", "-122.4476258"]], "BROADWAY": [["37.7987416", "-122.3998991"], ["37.7976479", "-122.4086392"]], "'MISSIONROCKRD": [["37.7729368", "-122.3898089"]], "TREATST": [["37.7557690", "-122.4132978"]], "'DIVISADEROST": [["37.7740721", "-122.4376238"]], "BUCHANANST": [["37.7734778", "-122.4273467"]], "'KIRKHAMST": [["37.7597955", "-122.4779532"]], "8THST": [["37.7713302", "-122.4054307"], ["37.7725615", "-122.4069632"], ["37.7666908", "-122.3997197"], ["37.7774649", "-122.4131792"], ["37.7774649", "-122.4131792"]], "3RDST": [["37.7729368", "-122.3898089"], ["37.7817709", "-122.3964107"], ["37.7292336", "-122.3925655"]], "'JONESST": [["37.8061684", "-122.4170939"]], "'MARKETST": [["37.7910528", "-122.3991866"]], "CUVIER": [["37.7334852", "-122.4286003"]], "'CHARLESST": [["37.7383545", "-122.4261058"]], "18THST": [["37.7615686", "-122.4238021"], ["37.7605308", "-122.4409180"]], "CAPPST": [["37.7555087", "-122.4176652"]], "MASONST": [["37.7972835", "-122.4119693"], ["37.8037856", "-122.4132525"], ["37.7881097", "-122.4100714"]], "4THST": [["37.7820607", "-122.4011821"], ["37.7852826", "-122.4052367"]], "'ALAMEDAST": [["37.7681764", "-122.4107552"]], "'CHURCHST": [["37.7677354", "-122.4289483"]], "'PARISST": [["37.7156442", "-122.4394706"]], "4THAV": [["37.7791925", "-122.4620020"]], "u'SYCAMORE": [["37.7625788", "-122.4216856"]], "'9THST": [["37.7694443", "-122.4062321"]], "ASHBURYST": [["37.7739150", "-122.4365240"]], "'FILLMOREST": [["37.7933533", "-122.4346951"]], "'8THAV": [["37.7808603", "-122.4664251"]], "'FULTONST": [["37.7732078", "-122.4701694"]], "OCEANAV": [["37.7247017", "-122.4599890"], ["37.7232099", "-122.4531372"], ["37.7230347", "-122.4496335"], ["37.7260346", "-122.4642215"]], "'LAKEVIEWAV": [["37.7161911", "-122.4504110"]], "8THAV": [["37.7660197", "-122.4653809"]], "MARKETST": [["37.7876655", "-122.4034605"], ["37.7876655", "-122.4034605"], ["37.7876655", "-122.4034605"], ["37.7876655", "-122.4034605"], ["37.7840081", "-122.4080920"], ["37.7840081", "-122.4080920"], ["37.7804664", "-122.4125602"], ["37.7785420", "-122.4148130"], ["37.7675884", "-122.4289385"], ["37.7730845", "-122.4220455"], ["37.7730845", "-122.4220455"], ["37.7730845", "-122.4220455"], ["37.7707539", "-122.4247672"], ["37.7707539", "-122.4247672"], ["37.7717843", "-122.4236948"], ["37.7717843", "-122.4236948"], ["37.7944889", "-122.3948012"], ["37.7725376", "-122.4227233"], ["37.7725376", "-122.4227233"], ["37.7725376", "-122.4227233"], ["37.7725376", "-122.4227233"], ["37.7752057", "-122.4192085"]], "'SENECAAV": [["37.7176754", "-122.4401492"]], "JACKSONST": [["37.7972266", "-122.3971684"]], "CORTLANDAV": [["37.7397234", "-122.4094832"]], "'BROOKDALEAV": [["37.7100883", "-122.4245787"]], "BEACHST": [["37.8081151", "-122.4090985"]], "'CALIFORNIAST": [["37.7889131", "-122.4338632"]], "TERRYFR": [["37.7690145", "-122.3862964"]], "LAKEMERCED": [["37.7085827", "-122.4867355"]], "SUTTERST": [["37.7879902", "-122.4185029"]], "MASONICAV": [["37.7801822", "-122.4473120"]], "'MISSISSIPPIST": [["37.7666137", "-122.3952032"]], "18THAV": [["37.7524181", "-122.4752821"]], "PHELPSST": [["37.7292077", "-122.4008435"], ["37.7398591", "-122.3912753"]], "OAKST": [["37.7729273", "-122.4390897"], ["37.7731321", "-122.4374385"], ["37.7731321", "-122.4374385"], ["37.7733533", "-122.4357496"]], "'QUINTARAST": [["37.7477995", "-122.4953671"]], "GEARYBL": [["37.7810375", "-122.4653564"], ["37.7808603", "-122.4664251"], ["37.7833959", "-122.4394308"], ["37.7877706", "-122.4051121"]], "'MISSIONST": [["37.7634242", "-122.4195575"]], "'VIRGINIAST": [["37.7431247", "-122.4214908"]], "FRANKLINST": [["37.7752318", "-122.4209760"], ["37.7946070", "-122.4248841"]], "SOUTHVA": [["37.7541700", "-122.4131527"], ["37.7525524", "-122.4132704"]], "9THST": [["37.7737855", "-122.4116385"], ["37.7762211", "-122.4147406"]], "'POLKST": [["37.7959845", "-122.4217921"]], "'HARRISONBL": [["37.7895240", "-122.3886044"]], "'5THST": [["37.7840081", "-122.4080920"]], "SANCHEZST": [["37.7667981", "-122.4310943"]], "PINEST": [["37.7896487", "-122.4205116"]], "'DIVISIONST": [["37.7698940", "-122.4033010"]], "'LARKINST": [["37.7786757", "-122.4166025"]], "'6THAV": [["37.7829523", "-122.4644277"]], "NOEST": [["37.7658768", "-122.4332402"]], "DIVISIONST": [["37.7694443", "-122.4062321"], ["37.7694443", "-122.4062321"]], "COLUMBUSAV": [["37.8037940", "-122.4151360"], ["37.7972670", "-122.4060980"], ["37.8019526", "-122.4126390"]], "TWINPEAKS": [["37.7594495", "-122.4473360"]], "'CUTLERST": [["37.7370173", "-122.5063388"]], "17THST": [["37.7628926", "-122.4285150"], ["37.7647373", "-122.4035493"], ["37.7634242", "-122.4195575"], ["37.7634242", "-122.4195575"]], "'FOLSOMST": [["37.7709294", "-122.4150466"]], "FULTONST": [["37.7743380", "-122.4583560"], ["37.7766543", "-122.4398489"], ["37.7760211", "-122.4447795"], ["37.7760211", "-122.4447795"]], "FELLST": [["37.7736412", "-122.4409112"], ["37.7738686", "-122.4392751"], ["37.7740721", "-122.4376238"], ["37.7740721", "-122.4376238"], ["37.7740721", "-122.4376238"], ["37.7740721", "-122.4376238"], ["37.7734303", "-122.4425649"]], "'CHESTNUTST": [["37.8037940", "-122.4151360"]], "'KANSASST": [["37.7647373", "-122.4035493"]], "'LINCOLNAV": [["37.7660197", "-122.4653809"]], "'2NDST": [["37.7818497", "-122.3920993"]], "7THST": [["37.7730575", "-122.4032376"]], "'ASHBURYST80": [["37.7739150", "-122.4365240"]], "'SVANNESSAV": [["37.7523682", "-122.4162688"]], "'VALENCIAST": [["37.7681528", "-122.4222248"]], "'CARROLLAV": [["37.7292077", "-122.4008435"]], "'17THST": [["37.7627477", "-122.4351586"]], "'46THAV": [["37.7529849", "-122.5054124"]], "'COLUMBUSAV": [["37.7972670", "-122.4060980"]], "'EWINGRD": [["37.7801822", "-122.4473120"]], "DUBOCEAV": [["37.7700039", "-122.4178412"]], "KINGST": [["37.7780083", "-122.3917215"], ["37.7780083", "-122.3917215"], ["37.7764938", "-122.3940593"]], "'BRADFORDST": [["37.7397234", "-122.4094832"]], "'THERESAST": [["37.7276495", "-122.4324302"]], "'7THST": [["37.7804664", "-122.4125602"]], "'37THAV": [["37.7339679", "-122.4944156"]], "'VANDYKEAV": [["37.7292336", "-122.3925655"]], "MISSION": [["37.7650530", "-122.4197149"], ["37.7634242", "-122.4195575"], ["37.7618402", "-122.4194024"], ["37.7554469", "-122.4187748"], ["37.7809857", "-122.4087183"], ["37.7762211", "-122.4147406"], ["37.7481117", "-122.4182746"], ["37.7410379", "-122.4228308"], ["37.7422213", "-122.4220772"], ["37.7099590", "-122.4493540"], ["37.7099590", "-122.4493540"], ["37.7185020", "-122.4395281"], ["37.7292307", "-122.4308447"], ["37.7095608", "-122.4505181"], ["37.7095608", "-122.4505181"], ["37.7211772", "-122.4374998"], ["37.7240048", "-122.4353196"], ["37.7176754", "-122.4401492"], ["37.7276495", "-122.4324302"], ["37.7431247", "-122.4214908"]], "MCALLISTERST": [["37.7800871", "-122.4201816"], ["37.7800871", "-122.4201816"]], "21STST": [["37.7569690", "-122.4200110"], ["37.7570308", "-122.4189302"]], "'SYCAMOREST": [["37.7625788", "-122.4216856"]], "'HENRYST": [["37.7667981", "-122.4310943"]], "'LOCUSTST": [["37.7875555", "-122.4519593"]], "NORLTHPOINTST": [["37.8053079", "-122.4236801"]], "POTREROST": [["37.7517318", "-122.4061480"]], "'GUERREROST": [["37.7680039", "-122.4244975"]], "'ELLISST": [["37.7850798", "-122.4111597"]], "'16THST": [["37.7650530", "-122.4197149"]], "u'LEAVENWORTH": [["37.7846631", "-122.4144723"]], "'9THAV": [["37.7828017", "-122.4676437"]], "STOCKTON": [["37.7976479", "-122.4086392"]], "'LYONST": [["37.7734303", "-122.4425649"]], "GREATHIGHWAY": [["37.7370173", "-122.5063388"]], "24THST": [["37.7526368", "-122.4118888"], ["37.7523682", "-122.4162688"], ["37.7516319", "-122.4285462"]], "'17THAV": [["37.7842709", "-122.4764544"]], "u'GOUGH": [["37.7730845", "-122.4220455"]], "'SCOTTST": [["37.7789495", "-122.4368706"]], "'OCTAVIAST": [["37.7717843", "-122.4236948"]], "BAYSHORE": [["37.7279635", "-122.4021642"]], "'SHRADERST": [["37.7646915", "-122.4512210"]], "VANNESS": [["37.7697121", "-122.4178256"], ["37.7571755", "-122.4167521"], ["37.7750560", "-122.4193210"], ["37.7866489", "-122.4215008"]], "TURKST": [["37.7834308", "-122.4091512"], ["37.7821707", "-122.4190036"]], "LINCOLN": [["37.7661683", "-122.4604571"]], "'SAGAMOREST": [["37.7114911", "-122.4556034"]], "'TAYLORST": [["37.7850798", "-122.4111597"]], "'FARRAGUTAV": [["37.7099590", "-122.4493540"]], "'MARIPOSAST": [["37.7628873", "-122.4128990"]], "ELLISST": [["37.7846631", "-122.4144723"], ["37.7850798", "-122.4111597"]], "DIVISADEROST": [["37.7722232", "-122.4371587"]], "5THST": [["37.7765851", "-122.3987720"], ["37.7802841", "-122.4034164"], ["37.7790490", "-122.4018621"]], "'BRANNANST": [["37.7765851", "-122.3987720"]], "SANCHESST": [["37.7660087", "-122.4310357"]], "LYONST": [["37.7762287", "-122.4431343"]], "YORKST": [["37.7560549", "-122.4085016"]], "'PINEST": [["37.7896487", "-122.4205116"]], "'CAPPST": [["37.7651267", "-122.4186097"]], "'ALABAMAST": [["37.7655043", "-122.4124415"]], "HAIGHTST": [["37.7700099", "-122.4469365"], ["37.7712749", "-122.4371285"], ["37.7712749", "-122.4371285"], ["37.7727315", "-122.4255433"], ["37.7714870", "-122.4353672"]], "'GRANTAV": [["37.8081151", "-122.4090985"]], "'20THST": [["37.7574921", "-122.4379429"]], "'BALBOAST": [["37.7765743", "-122.4780402"]], "'21STAV": [["37.7410921", "-122.4777116"]], "'GRAYSTONETE": [["37.7594495", "-122.4473360"]], "ARGUELLOBL": [["37.7761790", "-122.4584981"], ["37.7752481", "-122.4584281"], ["37.7884050", "-122.4593880"]], "'HOWTHST": [["37.7230347", "-122.4496335"]], "'LAKEST": [["37.7857403", "-122.4851044"]], "SACRAMENTOST": [["37.7875555", "-122.4519593"]], "'16THAV": [["37.7748760", "-122.4747175"]], "11THST": [["37.7726483", "-122.4150145"], ["37.7724134", "-122.4147158"]], "'MONTGOMERYST": [["37.7909760", "-122.4024281"]], "'KISSLINGST": [["37.7726483", "-122.4150145"]], "'18THAV": [["37.7823567", "-122.4773847"]], "'4THST": [["37.7783410", "-122.3965525"]], "GOUGH": [["37.7943931", "-122.4265472"]], "'STEINERST": [["37.7793637", "-122.4335920"]], "u'DRUMM": [["37.7972266", "-122.3971684"]], "POLKST": [["37.7863920", "-122.4198492"], ["37.8025005", "-122.4230936"], ["37.7896487", "-122.4205116"], ["37.7896487", "-122.4205116"], ["37.7821707", "-122.4190036"], ["37.7821707", "-122.4190036"], ["37.7968993", "-122.4219879"]], "'23RDST": [["37.7541700", "-122.4131527"]], "SANJOSE": [["37.7422964", "-122.4232184"], ["37.7161911", "-122.4504110"], ["37.7322760", "-122.4341322"], ["37.7114911", "-122.4556034"]], "'BRODERICKST": [["37.7878596", "-122.4421100"]], "'MAYNARDST": [["37.7292307", "-122.4308447"]], "'RONDELPL": [["37.7649612", "-122.4212475"]], "'24THST": [["37.7529898", "-122.4064139"]], "1STST": [["37.7910528", "-122.3991866"]], "CASTROST": [["37.7627477", "-122.4351586"]], "'BAYSHOREBL": [["37.7236223", "-122.4007830"]], "'SHOTWELLST": [["37.7684817", "-122.4167110"]], "ALEMANY": [["37.7347850", "-122.4108679"]], "'MONTEREYBL": [["37.7322760", "-122.4341322"]], "'MCALLISTERST": [["37.7752481", "-122.4584281"]], "WEBSTERST": [["37.7845195", "-122.4312314"], ["37.7760469", "-122.4295518"], ["37.7746514", "-122.4292685"], ["37.7807142", "-122.4304707"]], "CHENERYST": [["37.7383545", "-122.4261058"]], "'CENTRALAV": [["37.7760211", "-122.4447795"]], "'CORTLANDAV": [["37.7410379", "-122.4228308"]], "'30THST": [["37.7422964", "-122.4232184"]], "'8THST": [["37.7785420", "-122.4148130"]], "'HAROLDAV": [["37.7232099", "-122.4531372"]], "2NDST": [["37.7855505", "-122.3967177"], ["37.7876012", "-122.3993312"], ["37.7835245", "-122.3941704"]], "'ITALYAV": [["37.7185020", "-122.4395281"]], "POSTST": [["37.7874653", "-122.4149854"], ["37.7881097", "-122.4100714"], ["37.7845329", "-122.4380144"], ["37.7845329", "-122.4380144"]], "u'MARKET": [["37.7724134", "-122.4147158"]], "VALENCIA": [["37.7625788", "-122.4216856"]], "HARRISONST": [["37.7706429", "-122.4124994"], ["37.7700744", "-122.4130826"], ["37.7696315", "-122.4133320"], ["37.7590319", "-122.4125147"], ["37.7590319", "-122.4125147"], ["37.7574294", "-122.4123656"], ["37.7574294", "-122.4123656"], ["37.7628873", "-122.4128990"]], "HYDEST": [["37.7798005", "-122.4151553"], ["37.7785420", "-122.4148130"], ["37.7872400", "-122.4162600"]], "'STEUARTST": [["37.7944889", "-122.3948012"]], "'GOLDENGATEAV": [["37.7761790", "-122.4584981"]], "'HICKORYST": [["37.7746514", "-122.4292685"]], "'STILLMANST": [["37.7835245", "-122.3941704"]], "BUSHST": [["37.7909760", "-122.4024281"]], "'VANNESSAV": [["37.7782859", "-122.4198280"]], "'ALBIONST": [["37.7648602", "-122.4228830"]], "JONESST": [["37.7839385", "-122.4126255"]], "TAYLORST": [["37.7850798", "-122.4111597"], ["37.7832142", "-122.4107842"]], "'HYDEST": [["37.8048154", "-122.4201958"]], "'15THST": [["37.7662724", "-122.4264995"]], "'PAGEST": [["37.7734778", "-122.4273467"]], "BRYANTST": [["37.7681764", "-122.4107552"]], "TOWNSENDST": [["37.7806303", "-122.3905427"], ["37.7698940", "-122.4033010"]], "'OAKST": [["37.7752318", "-122.4209760"]], "7THAV": [["37.7622695", "-122.4640639"]], "'PRESIDIOTE": [["37.7884050", "-122.4593880"]], "SLOATBL": [["37.7339679", "-122.4944156"]], "'LAGUNAST": [["37.7727315", "-122.4255433"]], "'VALLEJOST": [["37.7968993", "-122.4219879"]], "25THAV": [["37.7781536", "-122.4845547"], ["37.7857403", "-122.4851044"]], "PAUL": [["37.7236223", "-122.4007830"]], "'POSTST": [["37.7872400", "-122.4162600"]], "'BROADWAYST": [["37.7972835", "-122.4119693"]], "'ASHBURYST": [["37.7700099", "-122.4469365"]], "'JUDAHST": [["37.7622695", "-122.4640639"]], "'VICKSBURGST": [["37.7516319", "-122.4285462"]], "'EUGENIAAV": [["37.7422213", "-122.4220772"]], "'CEDARST": [["37.7863920", "-122.4198492"]], "EUREKAST": [["37.7574921", "-122.4379429"]], "'BAKERST": [["37.7736412", "-122.4409112"]], "GOLDENGATEBRIDGE": [["37.7789495", "-122.4368706"], ["37.7793637", "-122.4335920"]], "ARGUELLOST": [["37.7813444", "-122.4588752"]], "'12THST": [["37.7700744", "-122.4130826"]], "12THST": [["37.7709294", "-122.4150466"]], "'BRYANTST": [["37.7656180", "-122.4105284"]], "'GEARYBL": [["37.7813444", "-122.4588752"]], "'EDDYST": [["37.7839385", "-122.4126255"]], "BAYST": [["37.8048154", "-122.4201958"]], "'ORTEGAST": [["37.7524181", "-122.4752821"]], "BOSWORTHST": [["37.7334852", "-122.4286003"]], "'6THST": [["37.7785241", "-122.4056342"]], "19THAV": [["37.7765743", "-122.4780402"]], "DOLORESST": [["37.7662724", "-122.4264995"]], "41STAV": [["37.7588030", "-122.5004339"]], "'2NDAV": [["37.7643813", "-122.4588124"]], "'JOHNMUIRDR": [["37.7085827", "-122.4867355"]], "'CARLST": [["37.7655600", "-122.4499600"]]}}}